Metadata-Version: 2.1
Name: strict-types
Version: 1.2
Summary: Type checker for functions and classes.
Home-page: https://github.com/badlock/strict-types
Author: Badlock
License: MIT
Platform: UNKNOWN
License-File: LICENSE
